{
  "results": {
    "svg": "<svg xmlns=\"http://www.w3.org/2000/svg\" viewBox=\"0 0 400 200\"><path fill=\"#51564e\" d=\"M0 0h400v200H0z\"/><g fill-opacity=\".5\"><path fill=\"#aeaa9b\" d=\"M293 169.8l70-73.1-116-121v196.8z\"/><path fill=\"#ecede9\" d=\"M112 123.4L77 84.1l60-15.7-21.5 20.8z\"/><path fill=\"#161309\" d=\"M374-24.2l50.2 28.7v185.6L340 224.2z\"/><path fill=\"#151e15\" d=\"M118.4 25.5L38.8 11.4-18.4 46l9.2 136z\"/><path fill=\"#c4d5d1\" d=\"M333.3 123.5l11.3-45.1-41.8-2.4-18 61.8z\"/><path fill=\"#1c160c\" d=\"M318.2 72.3l-44.3-.1 5.9 47.5 24.9-132.5z\"/><path fill=\"#2e3528\" d=\"M93.4 224.2H4.6l-8-29.3 183-101.8z\"/><path fill=\"#9b978d\" d=\"M352.5 49.1l8.6-45.6-22.8 6.7-15.7 47.5z\"/><path fill=\"#989f9b\" d=\"M55.3 185.7l-1.5-7.9-46-32.6 52.1 5.6z\"/><path fill=\"#7e6a4a\" d=\"M295.5 205.2l-82.6 19 139-118.4L424.2 88z\"/><path fill=\"#a4a89d\" d=\"M88.4 23.3l68.8-39.8-98.6-7.7 9.2 33.5z\"/><path fill=\"#9c9d94\" d=\"M107 73l-10.9 91.2L147.5 9.7l22.7 2.9z\"/><path fill=\"#fffffc\" d=\"M338.7 118.2l-9.6 8-37.6-2.5 2.7-10z\"/><path fill=\"#161d17\" d=\"M100 106.9l-124.2 22.3 27.6 12L89 123.7z\"/><path fill=\"#a5a8a1\" d=\"M65 57.1l48.6 30.3 20.6 33-14.7 7z\"/><path fill=\"#485e66\" d=\"M357.6 108.2l-80.2-12.8L199 224.2l-25-97.1z\"/><path fill=\"#c5ccc9\" d=\"M98.4 192l-18.8-1.7 15 34H74.1z\"/><path fill=\"#3e525c\" d=\"M242 89.8l42.2-5.9L174.9-24.2l-32.8 248.4z\"/><path fill=\"#d8d9d1\" d=\"M93.6 81.6l56.2 2.3L130 68.7 94 99.6z\"/><path fill=\"#1c251d\" d=\"M37.6 213.7l8.5-46.9-64-11.4-6.3 36.9z\"/><path fill=\"#2d2718\" d=\"M355.4 213.3L416-24.2l-61 170.4-52.8 55.3z\"/><path fill=\"#8d8f88\" d=\"M209.1 224.2l90.3-62-24.7-12.6 34.4 58.2z\"/><path fill=\"#12282f\" d=\"M242.8 206.6l-12.4-17.8 7.1-30 18 9z\"/><path fill=\"#929087\" d=\"M261.4 67.5l38-6-10-63.3-53 20z\"/><path fill=\"#202016\" d=\"M334.4 14.3l35.8-38.5-76.7 44.9 3.6 23.4z\"/></g></svg>",
    "optimizedSVG": "<svg xmlns=\"http://www.w3.org/2000/svg\" viewBox=\"0 0 400 200\"><path fill=\"#51564e\" d=\"M0 0h400v200H0z\"/><path fill=\"#aeaa9b\" d=\"M293 170l70-73L247-24v197z\"/><path fill=\"#ecede9\" d=\"M112 123L77 84l60-16-21 21z\"/><path fill=\"#161309\" d=\"M374-24l50 29v185l-84 34z\"/><path fill=\"#151e15\" d=\"M118 26L39 11l-57 35 9 136z\"/><path fill=\"#c4d5d1\" d=\"M333 124l12-46-42-2-18 62z\"/><path fill=\"#1c160c\" d=\"M318 72h-44l6 48 25-133z\"/><path fill=\"#2e3528\" d=\"M93 224H5l-8-29L180 93z\"/><path fill=\"#9b978d\" d=\"M353 49l8-45-23 6-15 48z\"/><path fill=\"#989f9b\" d=\"M55 186l-1-8-46-33 52 6z\"/><path fill=\"#7e6a4a\" d=\"M296 205l-83 19 139-118 72-18z\"/><path fill=\"#a4a89d\" d=\"M88 23l69-39-98-8 9 33z\"/><path fill=\"#9c9d94\" d=\"M107 73l-11 91 52-154 22 3z\"/><path fill=\"#fffffc\" d=\"M339 118l-10 8-38-2 3-10z\"/><path fill=\"#161d17\" d=\"M100 107l-124 22 27 12 86-17z\"/><path fill=\"#a5a8a1\" d=\"M65 57l49 30 20 33-15 7z\"/><path fill=\"#485e66\" d=\"M358 108l-81-13-78 129-25-97z\"/><path fill=\"#c5ccc9\" d=\"M98 192l-18-2 15 34H74z\"/><path fill=\"#3e525c\" d=\"M242 90l42-6L175-24l-33 248z\"/><path fill=\"#d8d9d1\" d=\"M94 82l56 2-20-15-36 31z\"/><path fill=\"#1c251d\" d=\"M38 214l8-47-64-12-6 37z\"/><path fill=\"#2d2718\" d=\"M355 213l61-237-61 170-53 56z\"/><path fill=\"#8d8f88\" d=\"M209 224l90-62-24-12 34 58z\"/><path fill=\"#12282f\" d=\"M243 207l-13-18 8-30 18 9z\"/><path fill=\"#929087\" d=\"M261 68l38-6-10-64-53 20z\"/><path fill=\"#202016\" d=\"M334 14l36-38-77 45 4 23z\"/></svg>"
  },
  "runs": {
    "Intel® Core™ i5-5257U": [
      {
        "duration": 5256,
        "sizes": {
          "original": 1757,
          "brotli": 737,
          "gzip": 813
        },
        "optimizedSizes": {
          "original": 1429,
          "brotli": 568,
          "gzip": 633
        }
      },
      {
        "duration": 4791,
        "sizes": {
          "original": 1795,
          "brotli": 763,
          "gzip": 836
        },
        "optimizedSizes": {
          "original": 1442,
          "brotli": 560,
          "gzip": 636
        }
      }
    ],
    "Intel® Core™ i7-6920HQ": [
      {
        "duration": 3373,
        "sizes": {
          "original": 1781,
          "brotli": 749,
          "gzip": 833
        },
        "optimizedSizes": {
          "original": 1448,
          "brotli": 577,
          "gzip": 644
        }
      }
    ]
  }
}